docker_jinja3/__init__.py
docker_jinja3/cli.py
docker_jinja3/conftree.py
docker_jinja3/main.py
docker_jinja3/contrib/__init__.py
docker_jinja3/contrib/basic.py
docker_jinja3/contrib/file.py
docker_jinja3-0.0.0.post3.data/scripts/dj
docker_jinja3-0.0.0.post3.dist-info/LICENSE
docker_jinja3-0.0.0.post3.dist-info/METADATA
docker_jinja3-0.0.0.post3.dist-info/WHEEL
docker_jinja3-0.0.0.post3.dist-info/top_level.txt
docker_jinja3-0.0.0.post3.dist-info/RECORD
