Metadata-Version: 2.1
Name: docker-jinja3
Version: 0.0.0.post3
Summary: Extend your dockerfiles with Jinja2 syntax to to more awesome dockerfiles
Home-page: https://github.com/eliorerz/docker-jinja3
Author: Elior Erez (originally written by Grokzen@gmail.com)
Author-email: elior123@gmail.com
License: MIT
Classifier: Development Status :: 3 - Alpha
Classifier: License :: OSI Approved :: MIT License
Classifier: Operating System :: OS Independent
Classifier: Programming Language :: Python
Classifier: Programming Language :: Python :: 3
Classifier: Programming Language :: Python :: 3.7
Classifier: Programming Language :: Python :: 3.8
Classifier: Programming Language :: Python :: 3.9
Classifier: Topic :: Software Development :: Build Tools
Classifier: Topic :: Software Development :: Testing
Requires-Python: >=3.7.0
License-File: LICENSE
Requires-Dist: pyyaml (==6.0)
Requires-Dist: Jinja2 (==3.1.2)
Requires-Dist: docopt (==0.6.2)
